<!DOCTYPE ui:UiBinder SYSTEM "http://dl.google.com/gwt/DTD/xhtml.ent">
<ui:UiBinder xmlns:ui="urn:ui:com.google.gwt.uibinder"
	xmlns:g="urn:import:com.google.gwt.user.client.ui"
	xmlns:m="urn:import:gwt.material.design.client.ui">
	<ui:style>

	</ui:style>
	<m:MaterialCard type="reveal"  ui:field="cardMusic">
		<m:link><m:MaterialLink ui:field="btnPlay" text="Play" /></m:link>
		<m:link><m:MaterialLink ui:field="btnDelete" text="Delete"/></m:link>
		<m:link><m:MaterialLink ui:field="btnUpdate" text="Update"/></m:link>
		<m:link><m:MaterialLink ui:field="btnShare" text="Share"/></m:link>
	</m:MaterialCard>
</ui:UiBinder> 